qtpyinheritance/__init__.py
qtpyinheritance/_version.py
qtpyinheritance/properties.py
qtpyinheritance/signals.py
qtpyinheritance/version.py
qtpyinheritance/tests/__init__.py
qtpyinheritance/tests/conftest.py
qtpyinheritance/tests/test_properties.py
qtpyinheritance/tests/test_signals.py
qtpyinheritance-0.0.3.dist-info/LICENSE
qtpyinheritance-0.0.3.dist-info/METADATA
qtpyinheritance-0.0.3.dist-info/WHEEL
qtpyinheritance-0.0.3.dist-info/top_level.txt
qtpyinheritance-0.0.3.dist-info/RECORD
