Metadata-Version: 2.1
Name: qtpyinheritance
Version: 0.0.3
Summary: Prototype qtpy inheritance-related tools
Author: SLAC National Accelerator Laboratory
License: Copyright (c) 2020, Ken Lauer
Classifier: Development Status :: 2 - Pre-Alpha
Classifier: Natural Language :: English
Classifier: Programming Language :: Python :: 3
Requires-Python: >=3.9
License-File: LICENSE
Requires-Dist: qtpy
Provides-Extra: doc
Requires-Dist: sphinx ; extra == 'doc'
Requires-Dist: ipython ; extra == 'doc'
Requires-Dist: matplotlib ; extra == 'doc'
Requires-Dist: numpydoc ; extra == 'doc'
Requires-Dist: sphinx-copybutton ; extra == 'doc'
Requires-Dist: sphinx-rtd-theme ; extra == 'doc'
Provides-Extra: test
Requires-Dist: coverage ; extra == 'test'
Requires-Dist: flake8 ; extra == 'test'
Requires-Dist: pytest ; extra == 'test'
Requires-Dist: pytest-qt ; extra == 'test'
Requires-Dist: pyqt5 ; extra == 'test'
